CHANGES.txt
buildout.cfg
setup.cfg
setup.py
evg/__init__.py
evg.recipe.activate.egg-info/PKG-INFO
evg.recipe.activate.egg-info/SOURCES.txt
evg.recipe.activate.egg-info/dependency_links.txt
evg.recipe.activate.egg-info/entry_points.txt
evg.recipe.activate.egg-info/namespace_packages.txt
evg.recipe.activate.egg-info/not-zip-safe
evg.recipe.activate.egg-info/requires.txt
evg.recipe.activate.egg-info/top_level.txt
evg/recipe/__init__.py
evg/recipe/activate/__init__.py