Metadata-Version: 1.0
Name: evg.recipe.activate
Version: 0.4
Summary: This recipe generates activation script for zc.buildout environment.
Home-page: http://github.com/generalov/evg.recipe.activate
Author: Evgeny V. Generalov
Author-email: e.generalov@gmail.com
License: ZPL 2.1
Keywords: buildout
Platform: UNKNOWN
Classifier: Framework :: Buildout
Classifier: Topic :: Software Development :: Build Tools
Classifier: License :: OSI Approved :: Zope Public License
Classifier: Development Status :: 5 - Production/Stable
